ocrmypdf_chromelens_ocr/__init__.py
ocrmypdf_chromelens_ocr/plugin.py
ocrmypdf_chromelens_ocr-1.0.1.dist-info/licenses/LICENSE
ocrmypdf_chromelens_ocr-1.0.1.dist-info/METADATA
ocrmypdf_chromelens_ocr-1.0.1.dist-info/WHEEL
ocrmypdf_chromelens_ocr-1.0.1.dist-info/entry_points.txt
ocrmypdf_chromelens_ocr-1.0.1.dist-info/top_level.txt
ocrmypdf_chromelens_ocr-1.0.1.dist-info/RECORD
