Metadata-Version: 2.4
Name: ocrmypdf-chromelens-ocr
Version: 1.0.1
Summary: OCRmyPDF plugin using Google Lens API for OCR
Author-email: Victor Sakovich <atlantos@gmail.com>
License: MIT License
Project-URL: Homepage, https://github.com/atlantos/OCRmyPDF-ChromeLens-Ocr
Project-URL: Bug Tracker, https://github.com/atlantos/OCRmyPDF-ChromeLens-Ocr/issues
Keywords: ocrmypdf,ocr,google-lens,pdf,plugin
Classifier: Development Status :: 4 - Beta
Classifier: Environment :: Console
Classifier: Intended Audience :: End Users/Desktop
Classifier: License :: OSI Approved :: MIT License
Classifier: Programming Language :: Python :: 3
Classifier: Topic :: Scientific/Engineering :: Image Recognition
Classifier: Topic :: Text Processing :: Indexing
Requires-Python: >=3.9
License-File: LICENSE
Requires-Dist: ocrmypdf>=16.0.0
Requires-Dist: requests
Requires-Dist: Pillow
Dynamic: license-file
